setup.py
txflask/__init__.py
txflask/app.py
txflask.egg-info/PKG-INFO
txflask.egg-info/SOURCES.txt
txflask.egg-info/dependency_links.txt
txflask.egg-info/requires.txt
txflask.egg-info/top_level.txt