Metadata-Version: 1.0
Name: txflask
Version: 0.1
Summary: txflask makes working with Twisted Web as easy as working with flask
Home-page: http://github.com/bmuller/txflask
Author: Brian Muller
Author-email: bamuller@gmail.com
License: MIT
Platform: UNKNOWN
